nuki_sesami/__about__.py
nuki_sesami/__init__.py
nuki_sesami/admin.py
nuki_sesami/bluetooth.py
nuki_sesami/bluetooth_client.py
nuki_sesami/clients.py
nuki_sesami/config.py
nuki_sesami/controller.py
nuki_sesami/error.py
nuki_sesami/lock.py
nuki_sesami/state.py
nuki_sesami/util.py
nuki_sesami-2.3.0.dist-info/METADATA
nuki_sesami-2.3.0.dist-info/WHEEL
nuki_sesami-2.3.0.dist-info/entry_points.txt
nuki_sesami-2.3.0.dist-info/licenses/LICENSE
nuki_sesami-2.3.0.dist-info/RECORD
