Metadata-Version: 2.4
Name: nuki-sesami
Version: 2.3.0
Summary: Open an electric door using Nuki smartlock status
Project-URL: Documentation, https://github.com/michelm/nuki-sesami#readme
Project-URL: Issues, https://github.com/michelm/nuki-sesami/issues
Project-URL: Source, https://github.com/michelm/nuki-sesami
Author-email: Michel Mooij <michel.mooij7@gmail.com>
License-Expression: MIT
License-File: LICENSE
Classifier: Development Status :: 4 - Beta
Classifier: License :: OSI Approved :: MIT License
Classifier: Operating System :: POSIX :: Linux
Classifier: Programming Language :: Python
Classifier: Programming Language :: Python :: 3.11
Classifier: Programming Language :: Python :: 3.12
Requires-Python: >=3.11
Requires-Dist: aiomqtt>=2.1.0
Requires-Dist: gpiozero>=2.0.1
Requires-Dist: paho-mqtt>=2.0.0
